{"id":"src/react-dom/index.js","dependencies":[{"name":"/Users/shunwuyu/lesson/lesson_show/react/diff/package.json","includedInParent":true,"mtime":1533217268725},{"name":"/Users/shunwuyu/lesson/lesson_show/react/diff/.babelrc","includedInParent":true,"mtime":1533217246410},{"name":"./render","loc":{"line":1,"column":19},"parent":"/Users/shunwuyu/lesson/lesson_show/react/diff/src/react-dom/index.js","resolved":"/Users/shunwuyu/lesson/lesson_show/react/diff/src/react-dom/render.js"}],"generated":{"js":"'use strict';\n\nObject.defineProperty(exports, \"__esModule\", {\n  value: true\n});\n\nvar _render = require('./render');\n\nvar _render2 = _interopRequireDefault(_render);\n\nfunction _interopRequireDefault(obj) { return obj && obj.__esModule ? obj : { default: obj }; }\n\nexports.default = {\n  render: _render2.default\n};","map":{"mappings":[{"generated":{"line":7,"column":0},"source":"src/react-dom/index.js","original":{"line":1,"column":0}},{"generated":{"line":13,"column":18},"source":"src/react-dom/index.js","original":{"line":3,"column":15}},{"name":"render","generated":{"line":14,"column":0},"source":"src/react-dom/index.js","original":{"line":4,"column":2}},{"generated":{"line":15,"column":0},"source":"src/react-dom/index.js","original":{"line":3,"column":15}}],"sources":{"src/react-dom/index.js":"import render from './render'\n\nexport default {\n  render\n}"},"lineCount":null}},"hash":"801433a507c0ec3c9ba25ecd12dc0d1f","cacheData":{"env":{}}}